test_xml_preferences.py
xml_preferences/__init__.py
xml_preferences/__main__.py
xml_preferences-1.1.6.dist-info/LICENSE
xml_preferences-1.1.6.dist-info/METADATA
xml_preferences-1.1.6.dist-info/WHEEL
xml_preferences-1.1.6.dist-info/top_level.txt
xml_preferences-1.1.6.dist-info/RECORD
