Metadata-Version: 2.1
Name: xml-preferences
Version: 1.1.6
Summary: xml-preferences reads and writes preferences infomation from XML files.
Author-email: Barry Scott <barry@barrys-emacs.org>
License: Apache-2.0
Project-URL: Homepage, https://github.com/barry-scott/xml-preferences
Project-URL: Bug Tracker, https://github.com/barry-scott/xml-preferences/issues
Keywords: development
Classifier: Intended Audience :: End Users/Desktop
Classifier: Topic :: Utilities
Classifier: Environment :: Console
Classifier: Programming Language :: Python :: 3
Requires-Python: >=3.10
License-File: LICENSE
